airtel/core.py
airtel-0.0.1.dist-info/LICENSE
airtel-0.0.1.dist-info/METADATA
airtel-0.0.1.dist-info/WHEEL
airtel-0.0.1.dist-info/top_level.txt
airtel-0.0.1.dist-info/RECORD
