Metadata-Version: 2.1
Name: airtel
Version: 0.0.1
Summary: airtel is a light open source module for your Airtel API.
Home-page: https://github.com/rivo2302/airtel_money_api
Author: rivo2302
Author-email: rivo2302@gmail.com
License: UNKNOWN
Project-URL: Homepage, https://github.com/rivo2302/airtel_money_api
Platform: UNKNOWN
Classifier: Programming Language :: Python :: 3
Classifier: License :: OSI Approved :: MIT License
Classifier: Operating System :: OS Independent
Requires-Python: >=3.7
License-File: LICENSE
Requires-Dist: requests
